mo_minus/__init__.py
mo_minus/minus.py
mo_minus-0.1.1.dist-info/METADATA
mo_minus-0.1.1.dist-info/WHEEL
mo_minus-0.1.1.dist-info/top_level.txt
mo_minus-0.1.1.dist-info/RECORD
