Metadata-Version: 2.1
Name: mo_minus
Version: 0.1.1
Summary: substract lambda
Author-email: Mingk42 <xoals123456t@gmail.com>
License: MIT
Project-URL: Homepage, https://github.com/Mingk42/mo_minus
Requires-Python: >=3.8
